rhamaa/__init__.py
rhamaa/__main__.py
rhamaa/cli.py
rhamaa/utils.py
rhamaa/commands/__init__.py
rhamaa/commands/cms/__init__.py
rhamaa/commands/cms/build.py
rhamaa/commands/cms/database.py
rhamaa/commands/cms/info.py
rhamaa/commands/cms/management.py
rhamaa/commands/cms/server.py
rhamaa/commands/cms/start.py
rhamaa/commands/cms/startapp.py
rhamaa/commands/cms/utils.py
rhamaa/templates/__init__.py
rhamaa/templates/cms/__init__.py
rhamaa/templates/cms/app_list.json
rhamaa/templates/cms/project_template_list.json
rhamaa/templates/cms/APPS_TEMPLATES/__init__.py
rhamaa/templates/cms/APPS_TEMPLATES/minimal/admin.py.tpl
rhamaa/templates/cms/APPS_TEMPLATES/minimal/apps.py.tpl
rhamaa/templates/cms/APPS_TEMPLATES/minimal/models.py.tpl
rhamaa/templates/cms/APPS_TEMPLATES/minimal/settings.py.tpl
rhamaa/templates/cms/APPS_TEMPLATES/minimal/tests.py.tpl
rhamaa/templates/cms/APPS_TEMPLATES/minimal/urls.py.tpl
rhamaa/templates/cms/APPS_TEMPLATES/minimal/views.py.tpl
rhamaa/templates/cms/APPS_TEMPLATES/wagtail/admin.py.tpl
rhamaa/templates/cms/APPS_TEMPLATES/wagtail/apps.py.tpl
rhamaa/templates/cms/APPS_TEMPLATES/wagtail/models.py.tpl
rhamaa/templates/cms/APPS_TEMPLATES/wagtail/settings.py.tpl
rhamaa/templates/cms/APPS_TEMPLATES/wagtail/tests.py.tpl
rhamaa/templates/cms/APPS_TEMPLATES/wagtail/urls.py.tpl
rhamaa/templates/cms/APPS_TEMPLATES/wagtail/views.py.tpl
rhamaa/templates/cms/APPS_TEMPLATES/wagtail/migrations/0001_initial.py.tpl
rhamaa/templates/cms/APPS_TEMPLATES/wagtail/templates/example_page.html.tpl
rhamaa/templates/cms/APPS_TEMPLATES/wagtail/templates/index.html.tpl
rhamaa-0.4.2.dist-info/licenses/LICENSE
rhamaa-0.4.2.dist-info/METADATA
rhamaa-0.4.2.dist-info/WHEEL
rhamaa-0.4.2.dist-info/entry_points.txt
rhamaa-0.4.2.dist-info/top_level.txt
rhamaa-0.4.2.dist-info/RECORD
