Metadata-Version: 2.4
Name: rhamaa
Version: 0.4.2
Summary: CLI tools to accelerate Wagtail web development with RhamaaCMS
Home-page: https://github.com/RhamaaCMS/RhamaaCLI
Author: RhamaaCMS Team
Author-email: Firdaus <firdaus@rhamaa.com>
Maintainer-email: Firdaus <firdaus@rhamaa.com>
License: MIT
Project-URL: Homepage, https://github.com/RhamaaCMS/RhamaaCLI
Project-URL: Documentation, https://github.com/RhamaaCMS/RhamaaCLI/wiki
Project-URL: Repository, https://github.com/RhamaaCMS/RhamaaCLI
Project-URL: Bug Reports, https://github.com/RhamaaCMS/RhamaaCLI/issues
Keywords: wagtail,django,cms,cli,rhamaa,code-generator
Classifier: Development Status :: 4 - Beta
Classifier: Intended Audience :: Developers
Classifier: Topic :: Software Development :: Code Generators
Classifier: Topic :: Internet :: WWW/HTTP :: Dynamic Content :: Content Management System
Classifier: License :: OSI Approved :: MIT License
Classifier: Programming Language :: Python :: 3
Classifier: Programming Language :: Python :: 3.7
Classifier: Programming Language :: Python :: 3.8
Classifier: Programming Language :: Python :: 3.9
Classifier: Programming Language :: Python :: 3.10
Classifier: Programming Language :: Python :: 3.11
Classifier: Programming Language :: Python :: 3.12
Classifier: Framework :: Django
Classifier: Framework :: Wagtail
Requires-Python: >=3.7
License-File: LICENSE
Requires-Dist: click>=8.0.0
Requires-Dist: rich>=12.0.0
Requires-Dist: requests>=2.25.0
Requires-Dist: gitpython>=3.1.0
Provides-Extra: cms
Requires-Dist: wagtail>=5.0; extra == "cms"
Provides-Extra: cv
Requires-Dist: ultralytics>=8.0.0; extra == "cv"
Requires-Dist: opencv-python>=4.8.0; extra == "cv"
Provides-Extra: dev
Requires-Dist: pytest>=6.0; extra == "dev"
Requires-Dist: pytest-cov; extra == "dev"
Requires-Dist: black; extra == "dev"
Requires-Dist: flake8; extra == "dev"
Requires-Dist: twine; extra == "dev"
Requires-Dist: build; extra == "dev"
Dynamic: author
Dynamic: home-page
Dynamic: license-file
Dynamic: requires-python
